tactrandom-1.0.6.dist-info/licenses/LICENSE
trandom/__init__.py
trandom/__main__.py
trandom/cli.py
trandom/config.py
trandom/documentor.py
trandom/exceptions.py
trandom/factory.py
trandom/generator.py
trandom/proxy.py
trandom/proxy.pyi
trandom/py.typed
trandom/typing.py
trandom/contrib/__init__.py
trandom/contrib/pytest/__init__.py
trandom/contrib/pytest/plugin.py
trandom/decode/__init__.py
trandom/decode/codes.py
trandom/providers/__init__.py
trandom/providers/address/__init__.py
trandom/providers/address/az_AZ/__init__.py
trandom/providers/address/bn_BD/__init__.py
trandom/providers/address/cs_CZ/__init__.py
trandom/providers/address/da_DK/__init__.py
trandom/providers/address/de/__init__.py
trandom/providers/address/de_AT/__init__.py
trandom/providers/address/de_CH/__init__.py
trandom/providers/address/de_DE/__init__.py
trandom/providers/address/el_GR/__init__.py
trandom/providers/address/en/__init__.py
trandom/providers/address/en_AU/__init__.py
trandom/providers/address/en_BD/__init__.py
trandom/providers/address/en_CA/__init__.py
trandom/providers/address/en_GB/__init__.py
trandom/providers/address/en_IE/__init__.py
trandom/providers/address/en_IN/__init__.py
trandom/providers/address/en_MS/__init__.py
trandom/providers/address/en_NZ/__init__.py
trandom/providers/address/en_PH/__init__.py
trandom/providers/address/en_US/__init__.py
trandom/providers/address/es/__init__.py
trandom/providers/address/es_AR/__init__.py
trandom/providers/address/es_CL/__init__.py
trandom/providers/address/es_CO/__init__.py
trandom/providers/address/es_ES/__init__.py
trandom/providers/address/es_MX/__init__.py
trandom/providers/address/fa_IR/__init__.py
trandom/providers/address/fi_FI/__init__.py
trandom/providers/address/fil_PH/__init__.py
trandom/providers/address/fr_CA/__init__.py
trandom/providers/address/fr_CH/__init__.py
trandom/providers/address/fr_FR/__init__.py
trandom/providers/address/he_IL/__init__.py
trandom/providers/address/hi_IN/__init__.py
trandom/providers/address/hr_HR/__init__.py
tactrandom-1.0.6.dist-info/METADATA
tactrandom-1.0.6.dist-info/WHEEL
tactrandom-1.0.6.dist-info/top_level.txt
tactrandom-1.0.6.dist-info/RECORD
