Metadata-Version: 2.4
Name: tactrandom
Version: 1.0.6
Summary: TRandom - Python package that generates fake data for you
Home-page: https://github.com/tactlabs/tact-random
Author: Raja CSP Raman
Author-email: Raja CSP Raman <raja.csp@gmail.com>
License: MIT
Project-URL: Homepage, https://github.com/tactlabs/tact-random
Project-URL: Repository, https://github.com/tactlabs/tact-random
Project-URL: Issues, https://github.com/tactlabs/tact-random/issues
Keywords: faker,fake,data,test,random,generator,trandom
Classifier: Development Status :: 4 - Beta
Classifier: Intended Audience :: Developers
Classifier: License :: OSI Approved :: MIT License
Classifier: Operating System :: OS Independent
Classifier: Programming Language :: Python :: 3
Classifier: Programming Language :: Python :: 3.10
Classifier: Programming Language :: Python :: 3.11
Classifier: Programming Language :: Python :: 3.12
Classifier: Topic :: Software Development :: Testing
Classifier: Topic :: Software Development :: Libraries :: Python Modules
Requires-Python: >=3.10
License-File: LICENSE
Requires-Dist: numpy
Requires-Dist: pandas
Dynamic: author
Dynamic: home-page
Dynamic: license-file
Dynamic: requires-python
